{
	"animations": [
		{
			"offsets": [494, 506],
			"loop": false,
			"fps": 24,
			"anim": "singDOWN-alt",
			"indices": [],
			"name": "down"
		},
		{
			"offsets": [464, 491],
			"loop": false,
			"fps": 12,
			"anim": "singUPmiss",
			"indices": [],
			"name": "miss"
		},
		{
			"offsets": [501, 516],
			"loop": false,
			"fps": 3,
			"anim": "singUP",
			"indices": [],
			"name": "up"
		},
		{
			"offsets": [485, 508],
			"loop": false,
			"fps": 12,
			"anim": "singRIGHTmiss",
			"indices": [],
			"name": "miss"
		},
		{
			"offsets": [361, 500],
			"loop": false,
			"fps": 3,
			"anim": "singRIGHT",
			"indices": [],
			"name": "right"
		},
		{
			"offsets": [497, 474],
			"loop": false,
			"fps": 12,
			"anim": "singDOWNmiss",
			"indices": [],
			"name": "miss"
		},
		{
			"offsets": [493, 515],
			"loop": false,
			"fps": 3,
			"anim": "singLEFT",
			"indices": [],
			"name": "left"
		},
		{
			"offsets": [490, 496],
			"loop": false,
			"fps": 6,
			"anim": "singDOWN",
			"indices": [],
			"name": "down"
		},
		{
			"offsets": [502, 502],
			"loop": false,
			"fps": 12,
			"anim": "singLEFTmiss",
			"indices": [],
			"name": "miss"
		},
		{
			"offsets": [477, 491],
			"loop": false,
			"fps": 24,
			"anim": "singUP-alt",
			"indices": [],
			"name": "up"
		},
		{
			"offsets": [454, 519],
			"indices": [1, 2, 3, 1, 2, 2, 3],
			"fps": 6,
			"anim": "idle",
			"loop": false,
			"name": "idle"
		}
	],
	"vocals_file": "",
	"no_antialiasing": false,
	"image": "characters/zefer",
	"position": [170, 430],
	"healthicon": "Zefer",
	"flip_x": false,
	"healthbar_colors": [255, 74, 236],
	"camera_position": [110, -140],
	"sing_duration": 4,
	"scale": 0.4,
	"_editor_isPlayer": true
}